mastodoner/__init__.py
mastodoner/cli.py
mastodoner/crawler.py
mastodoner/version.py
mastodoner-0.0.2.dist-info/LICENSE
mastodoner-0.0.2.dist-info/METADATA
mastodoner-0.0.2.dist-info/WHEEL
mastodoner-0.0.2.dist-info/entry_points.txt
mastodoner-0.0.2.dist-info/top_level.txt
mastodoner-0.0.2.dist-info/RECORD
