Metadata-Version: 2.1
Name: mastodoner
Version: 0.0.2
Summary: A package for crawling Mastodon instances
Home-page: https://github.com/harisbinzia/mastodoner
Author: Haris Bin Zia
Author-email: harisbinzia@hotmail.com
Classifier: Programming Language :: Python :: 3
Classifier: License :: OSI Approved :: MIT License
Classifier: Operating System :: OS Independent
Requires-Python: >=3.8
License-File: LICENSE
Requires-Dist: requests
